itkwidgets/__init__.py
itkwidgets/_transform_types.py
itkwidgets/_version.py
itkwidgets/cm.py
itkwidgets/lut.py
itkwidgets/trait_types.py
itkwidgets/widget_checkerboard.py
itkwidgets/widget_compare.py
itkwidgets/widget_label_statistics.py
itkwidgets/widget_line_profiler.py
itkwidgets/widget_viewer.py
itkwidgets/static/8161bfdec7ecee94a04f.worker.js.map
itkwidgets/static/e2e5b834a5dc5a56c944.worker.js.map
itkwidgets/static/extension.js
itkwidgets/static/index.js
itkwidgets/static/index.js.map
itkwidgets/static/itk/Pipelines/ZstdDecompress.js
itkwidgets/static/itk/Pipelines/ZstdDecompressWasm.js
itkwidgets/static/itk/Pipelines/ZstdDecompressWasm.wasm
itkwidgets/static/itk/WebWorkers/Pipeline.worker.js
itkwidgets-0.32.6.data/data/etc/jupyter/nbconfig/notebook.d/itkwidgets.json
itkwidgets-0.32.6.data/data/share/jupyter/nbextensions/itkwidgets/extension.js
itkwidgets-0.32.6.data/data/share/jupyter/nbextensions/itkwidgets/index.js
itkwidgets-0.32.6.data/data/share/jupyter/nbextensions/itkwidgets/index.js.map
itkwidgets-0.32.6.data/data/share/jupyter/nbextensions/itkwidgets/itk/Pipelines/ZstdDecompress.js
itkwidgets-0.32.6.data/data/share/jupyter/nbextensions/itkwidgets/itk/Pipelines/ZstdDecompressWasm.js
itkwidgets-0.32.6.data/data/share/jupyter/nbextensions/itkwidgets/itk/Pipelines/ZstdDecompressWasm.wasm
itkwidgets-0.32.6.data/data/share/jupyter/nbextensions/itkwidgets/itk/WebWorkers/Pipeline.worker.js
itkwidgets-0.32.6.dist-info/LICENSE
itkwidgets-0.32.6.dist-info/METADATA
itkwidgets-0.32.6.dist-info/WHEEL
itkwidgets-0.32.6.dist-info/top_level.txt
itkwidgets-0.32.6.dist-info/RECORD
