Metadata-Version: 2.1
Name: itkwidgets
Version: 0.32.6
Summary: Interactive Jupyter widgets to visualize images, point sets, and meshes in 2D and 3D
Home-page: https://github.com/InsightSoftwareConsortium/itkwidgets
Author: Matthew McCormick
Author-email: matt.mccormick@kitware.com
License: UNKNOWN
Keywords: ipython,jupyter,jupyterlab-extension,widgets,itk,imaging,visualization,webgl
Platform: UNKNOWN
Classifier: License :: OSI Approved :: Apache Software License
Classifier: Programming Language :: Python
Classifier: Development Status :: 4 - Beta
Classifier: Framework :: IPython
Classifier: Intended Audience :: Developers
Classifier: Intended Audience :: Science/Research
Classifier: Topic :: Multimedia :: Graphics
Classifier: Programming Language :: Python :: 3
Classifier: Programming Language :: Python :: 3.7
Classifier: Programming Language :: Python :: 3.8
Classifier: Programming Language :: Python :: 3.9
Classifier: Programming Language :: Python :: 3.10
Classifier: Programming Language :: Python :: 3.11
License-File: LICENSE
Requires-Dist: colorcet
Requires-Dist: itk-core (>=5.3.0)
Requires-Dist: itk-filtering (>=5.3.0)
Requires-Dist: itk-numerics (>=5.3.0)
Requires-Dist: itk-meshtopolydata (>=0.10)
Requires-Dist: ipydatawidgets (<4.3.3,>=4.0.1)
Requires-Dist: ipywidgets (>=7.5.1)
Requires-Dist: ipympl (>=0.4.1)
Requires-Dist: matplotlib
Requires-Dist: numpy
Requires-Dist: six
Requires-Dist: zstandard
Requires-Dist: traitlets (<5.7.0)
Requires-Dist: notebook (<6.5.0)
Requires-Dist: ipywidgets (<8.0.0)
